test_package/__init__.py
test_package/inputer.py
test_package/output/__init__.py
test_package/output/printer.py
test_package_9991-1.1.0.dist-info/LICENSE
test_package_9991-1.1.0.dist-info/METADATA
test_package_9991-1.1.0.dist-info/WHEEL
test_package_9991-1.1.0.dist-info/top_level.txt
test_package_9991-1.1.0.dist-info/RECORD
