Metadata-Version: 2.1
Name: test-package-9991
Version: 1.1.0
Summary: test package for publishing
Author-email: qianyunli <qianyunli0@outlook.com>
License: MIT License
Keywords: test
Classifier: License :: OSI Approved :: MIT License
Classifier: Programming Language :: Python :: 3
Requires-Python: >=3.8
License-File: LICENSE
Requires-Dist: numpy
Requires-Dist: PyQt5
Provides-Extra: dev
Requires-Dist: pandas ; extra == 'dev'
